tkAppFramework/HelpModel.py
tkAppFramework/ObserverPatternBase.py
tkAppFramework/SimulatorModel.py
tkAppFramework/__init__.py
tkAppFramework/dummy_AppViewMgr.py
tkAppFramework/main.py
tkAppFramework/model.py
tkAppFramework/sim_adapter.py
tkAppFramework/tkApp.py
tkAppFramework/tkHelpViewManager.py
tkAppFramework/tkSimulatorApp.py
tkAppFramework/tkSimulatorViewManager.py
tkAppFramework/tkUserQueryReceiver.py
tkAppFramework/tkUserQueryToolEmbedded.py
tkAppFramework/tkUserQueryToolModal.py
tkAppFramework/tkUserQueryViewManager.py
tkAppFramework/tkViewManager.py
tkappframework-0.9.3.data/data/Help/tkAppFramework/HelpFile.txt
tkappframework-0.9.3.data/data/Help/tkAppFramework/SimApp_HelpFile.txt
tkappframework-0.9.3.dist-info/METADATA
tkappframework-0.9.3.dist-info/WHEEL
tkappframework-0.9.3.dist-info/entry_points.txt
tkappframework-0.9.3.dist-info/licenses/LICENSE
tkappframework-0.9.3.dist-info/RECORD
