Metadata-Version: 2.4
Name: tkAppFramework
Version: 0.9.3
Summary: tkAppFramework facilitates the creation of python GUI applications using tkinter.
Keywords: query,GUI,desktop,framework,simulator,tkinter,help,MVC
Author-Email: "Kevin R. Geurts" <kevin.r.geurts@gmail.com>
License-Expression: MIT
License-File: LICENSE
Classifier: Programming Language :: Python :: 3
Classifier: Operating System :: OS Independent
Classifier: Development Status :: 4 - Beta
Classifier: Environment :: Win32 (MS Windows)
Classifier: Environment :: X11 Applications
Classifier: Intended Audience :: Developers
Classifier: Topic :: Software Development :: Libraries :: Python Modules
Classifier: Topic :: Software Development :: User Interfaces
Project-URL: Homepage, https://github.com/KevinRGeurts/tkAppFramework
Project-URL: Issues, https://github.com/KevinRGeurts/tkAppFramework/issues
Requires-Python: >=3.12
Requires-Dist: UserResponseCollector>=1.1.0
